{
    "host_memory_GB": 857.241943359375,
    "host_cpu_count": 288,
    "host_processor_name": "aarch64",
    "potential_caching": 1,
    "host_cpuinfo": {
        "BogoMIPS": "2000.00",
        "Features": "fp asimd evtstrm aes pmull sha1 sha2 crc32 atomics fphp asimdhp cpuid asimdrdm jscvt fcma lrcpc dcpop sha3 sm3 sm4 asimddp sha512 sve asimdfhm dit uscat ilrcpc flagm ssbs sb dcpodp sve2 sveaes svepmull svebitperm svesha3 svesm4 flagm2 frint svei8mm svebf16 i8mm bf16 dgh",
        "CPU implementer": "0x41",
        "CPU architecture": "8",
        "CPU variant": "0x0",
        "CPU part": "0xd4f",
        "CPU revision": "0"
    },
    "host_meminfo": {
        "MemTotal": "898883328 kB",
        "MemFree": "847638528 kB",
        "MemAvailable": "824117952 kB",
        "Buffers": "647040 kB",
        "Cached": "27832512 kB",
        "SwapCached": "0 kB",
        "Active": "5055168 kB",
        "Inactive": "27387072 kB",
        "Active(anon)": "4180608 kB",
        "Inactive(anon)": "0 kB",
        "Active(file)": "874560 kB",
        "Inactive(file)": "27387072 kB",
        "Unevictable": "3072 kB",
        "Mlocked": "0 kB",
        "SwapTotal": "0 kB",
        "SwapFree": "0 kB",
        "Zswap": "0 kB",
        "Zswapped": "0 kB",
        "Dirty": "1152 kB",
        "Writeback": "0 kB",
        "AnonPages": "3968000 kB",
        "Mapped": "634240 kB",
        "Shmem": "217920 kB",
        "KReclaimable": "564416 kB",
        "Slab": "5223296 kB",
        "SReclaimable": "564416 kB",
        "SUnreclaim": "4658880 kB",
        "KernelStack": "240640 kB",
        "PageTables": "25088 kB",
        "SecPageTables": "0 kB",
        "NFS_Unstable": "0 kB",
        "Bounce": "0 kB",
        "WritebackTmp": "0 kB",
        "CommitLimit": "449441664 kB",
        "Committed_AS": "8414336 kB",
        "VmallocTotal": "137168158720 kB",
        "VmallocUsed": "822528 kB",
        "VmallocChunk": "0 kB",
        "Percpu": "1640448 kB",
        "HardwareCorrupted": "0 kB",
        "AnonHugePages": "0 kB",
        "ShmemHugePages": "0 kB",
        "ShmemPmdMapped": "0 kB",
        "FileHugePages": "0 kB",
        "FilePmdMapped": "0 kB",
        "CmaTotal": "0 kB",
        "CmaFree": "0 kB",
        "HugePages_Total": "0",
        "HugePages_Free": "0",
        "HugePages_Rsvd": "0",
        "HugePages_Surp": "0",
        "Hugepagesize": "524288 kB",
        "Hugetlb": "0 kB"
    },
    "1": {
        "load": {
            "block1": [
                4.51412034034729,
                0.015128374099731445,
                0.0013415813446044922,
                0.0012853145599365234,
                0.8994431495666504,
                0.0007688999176025391
            ],
            "eval": []
        },
        "proc": {
            "block1": [
                4.837601661682129,
                0.33853816986083984,
                0.32472801208496094,
                0.32466697692871094,
                1.2228317260742188,
                0.3241255283355713
            ],
            "eval": []
        },
        "throughput": {
            "block1": 10.138069476204905,
            "eval": 0.0
        },
        "au": {
            "block1": 58.53830807891154,
            "eval": 0.0
        },
        "compute": {
            "block1": [
                0.3233661651611328,
                0.3233602046966553,
                0.32335615158081055,
                0.32335424423217773,
                0.3233458995819092,
                0.323333740234375
            ],
            "eval": []
        },
        "host_meminfo": {
            "MemTotal": "898883328 kB",
            "MemFree": "847590144 kB",
            "MemAvailable": "824069568 kB",
            "Buffers": "647040 kB",
            "Cached": "27832512 kB",
            "SwapCached": "0 kB",
            "Active": "5087424 kB",
            "Inactive": "27387072 kB",
            "Active(anon)": "4212864 kB",
            "Inactive(anon)": "0 kB",
            "Active(file)": "874560 kB",
            "Inactive(file)": "27387072 kB",
            "Unevictable": "3072 kB",
            "Mlocked": "0 kB",
            "SwapTotal": "0 kB",
            "SwapFree": "0 kB",
            "Zswap": "0 kB",
            "Zswapped": "0 kB",
            "Dirty": "1152 kB",
            "Writeback": "0 kB",
            "AnonPages": "4000256 kB",
            "Mapped": "634240 kB",
            "Shmem": "217920 kB",
            "KReclaimable": "564416 kB",
            "Slab": "5223296 kB",
            "SReclaimable": "564416 kB",
            "SUnreclaim": "4658880 kB",
            "KernelStack": "240640 kB",
            "PageTables": "25088 kB",
            "SecPageTables": "0 kB",
            "NFS_Unstable": "0 kB",
            "Bounce": "0 kB",
            "WritebackTmp": "0 kB",
            "CommitLimit": "449441664 kB",
            "Committed_AS": "8451264 kB",
            "VmallocTotal": "137168158720 kB",
            "VmallocUsed": "822528 kB",
            "VmallocChunk": "0 kB",
            "Percpu": "1640448 kB",
            "HardwareCorrupted": "0 kB",
            "AnonHugePages": "0 kB",
            "ShmemHugePages": "0 kB",
            "ShmemPmdMapped": "0 kB",
            "FileHugePages": "0 kB",
            "FilePmdMapped": "0 kB",
            "CmaTotal": "0 kB",
            "CmaFree": "0 kB",
            "HugePages_Total": "0",
            "HugePages_Free": "0",
            "HugePages_Rsvd": "0",
            "HugePages_Surp": "0",
            "Hugepagesize": "524288 kB",
            "Hugetlb": "0 kB"
        },
        "end": "2025-11-30T18:45:27.012420"
    },
    "2": {
        "load": {
            "block1": [
                4.332702875137329,
                0.018008947372436523,
                0.0011501312255859375,
                0.0011627674102783203,
                0.896294116973877,
                0.0007660388946533203
            ],
            "eval": []
        },
        "proc": {
            "block1": [
                4.656145334243774,
                0.3414170742034912,
                0.32453274726867676,
                0.32454609870910645,
                1.21968412399292,
                0.32412075996398926
            ],
            "eval": []
        },
        "throughput": {
            "block1": 10.326908179026866,
            "eval": 0.0
        },
        "au": {
            "block1": 59.6286215906359,
            "eval": 0.0
        },
        "compute": {
            "block1": [
                0.3233668804168701,
                0.3233606815338135,
                0.32335376739501953,
                0.32335448265075684,
                0.3233463764190674,
                0.3233332633972168
            ],
            "eval": []
        },
        "host_meminfo": {
            "MemTotal": "898883328 kB",
            "MemFree": "846272256 kB",
            "MemAvailable": "822751808 kB",
            "Buffers": "647168 kB",
            "Cached": "27863808 kB",
            "SwapCached": "0 kB",
            "Active": "6363392 kB",
            "Inactive": "27387264 kB",
            "Active(anon)": "5488832 kB",
            "Inactive(anon)": "0 kB",
            "Active(file)": "874560 kB",
            "Inactive(file)": "27387264 kB",
            "Unevictable": "3072 kB",
            "Mlocked": "0 kB",
            "SwapTotal": "0 kB",
            "SwapFree": "0 kB",
            "Zswap": "0 kB",
            "Zswapped": "0 kB",
            "Dirty": "1280 kB",
            "Writeback": "0 kB",
            "AnonPages": "5275584 kB",
            "Mapped": "643392 kB",
            "Shmem": "249152 kB",
            "KReclaimable": "564416 kB",
            "Slab": "5231616 kB",
            "SReclaimable": "564416 kB",
            "SUnreclaim": "4667200 kB",
            "KernelStack": "245696 kB",
            "PageTables": "36032 kB",
            "SecPageTables": "0 kB",
            "NFS_Unstable": "0 kB",
            "Bounce": "0 kB",
            "WritebackTmp": "0 kB",
            "CommitLimit": "449441664 kB",
            "Committed_AS": "30889664 kB",
            "VmallocTotal": "137168158720 kB",
            "VmallocUsed": "827072 kB",
            "VmallocChunk": "0 kB",
            "Percpu": "1640448 kB",
            "HardwareCorrupted": "0 kB",
            "AnonHugePages": "0 kB",
            "ShmemHugePages": "0 kB",
            "ShmemPmdMapped": "0 kB",
            "FileHugePages": "0 kB",
            "FilePmdMapped": "0 kB",
            "CmaTotal": "0 kB",
            "CmaFree": "0 kB",
            "HugePages_Total": "0",
            "HugePages_Free": "0",
            "HugePages_Rsvd": "0",
            "HugePages_Surp": "0",
            "Hugepagesize": "524288 kB",
            "Hugetlb": "0 kB"
        },
        "end": "2025-11-30T18:45:34.387534"
    },
    "3": {
        "load": {
            "block1": [
                4.2925755977630615,
                0.017876148223876953,
                0.0011203289031982422,
                0.0011296272277832031,
                0.9041182994842529,
                0.0007669925689697266
            ],
            "eval": []
        },
        "proc": {
            "block1": [
                4.616000652313232,
                0.34128451347351074,
                0.32450270652770996,
                0.3245120048522949,
                1.227508306503296,
                0.32412242889404297
            ],
            "eval": []
        },
        "throughput": {
            "block1": 10.378410173059942,
            "eval": 0.0
        },
        "au": {
            "block1": 59.925875639192036,
            "eval": 0.0
        },
        "compute": {
            "block1": [
                0.3233606815338135,
                0.32335972785949707,
                0.32335376739501953,
                0.32335472106933594,
                0.32334375381469727,
                0.3233332633972168
            ],
            "eval": []
        },
        "host_meminfo": {
            "MemTotal": "898883328 kB",
            "MemFree": "845839104 kB",
            "MemAvailable": "822318656 kB",
            "Buffers": "647232 kB",
            "Cached": "27866368 kB",
            "SwapCached": "0 kB",
            "Active": "6642496 kB",
            "Inactive": "27387328 kB",
            "Active(anon)": "5767936 kB",
            "Inactive(anon)": "0 kB",
            "Active(file)": "874560 kB",
            "Inactive(file)": "27387328 kB",
            "Unevictable": "3072 kB",
            "Mlocked": "0 kB",
            "SwapTotal": "0 kB",
            "SwapFree": "0 kB",
            "Zswap": "0 kB",
            "Zswapped": "0 kB",
            "Dirty": "1216 kB",
            "Writeback": "0 kB",
            "AnonPages": "5519296 kB",
            "Mapped": "644608 kB",
            "Shmem": "251712 kB",
            "KReclaimable": "564416 kB",
            "Slab": "5242496 kB",
            "SReclaimable": "564416 kB",
            "SUnreclaim": "4678080 kB",
            "KernelStack": "247744 kB",
            "PageTables": "47040 kB",
            "SecPageTables": "0 kB",
            "NFS_Unstable": "0 kB",
            "Bounce": "0 kB",
            "WritebackTmp": "0 kB",
            "CommitLimit": "449441664 kB",
            "Committed_AS": "31079616 kB",
            "VmallocTotal": "137168158720 kB",
            "VmallocUsed": "829120 kB",
            "VmallocChunk": "0 kB",
            "Percpu": "1640448 kB",
            "HardwareCorrupted": "0 kB",
            "AnonHugePages": "0 kB",
            "ShmemHugePages": "0 kB",
            "ShmemPmdMapped": "0 kB",
            "FileHugePages": "0 kB",
            "FilePmdMapped": "0 kB",
            "CmaTotal": "0 kB",
            "CmaFree": "0 kB",
            "HugePages_Total": "0",
            "HugePages_Free": "0",
            "HugePages_Rsvd": "0",
            "HugePages_Surp": "0",
            "Hugepagesize": "524288 kB",
            "Hugetlb": "0 kB"
        },
        "end": "2025-11-30T18:45:41.706903"
    },
    "4": {
        "load": {
            "block1": [
                4.283251523971558,
                0.020105600357055664,
                0.0011441707611083984,
                0.0011370182037353516,
                0.8911066055297852,
                0.0007593631744384766
            ],
            "eval": []
        },
        "proc": {
            "block1": [
                4.606677532196045,
                0.3435099124908447,
                0.3245260715484619,
                0.32451844215393066,
                1.2144966125488281,
                0.3241150379180908
            ],
            "eval": []
        },
        "throughput": {
            "block1": 10.313725221567607,
            "eval": 0.0
        },
        "au": {
            "block1": 59.55228229695074,
            "eval": 0.0
        },
        "compute": {
            "block1": [
                0.32335996627807617,
                0.32335734367370605,
                0.32335400581359863,
                0.3233528137207031,
                0.3233456611633301,
                0.3233327865600586
            ],
            "eval": []
        },
        "host_meminfo": {
            "MemTotal": "898883328 kB",
            "MemFree": "845792320 kB",
            "MemAvailable": "822271872 kB",
            "Buffers": "647232 kB",
            "Cached": "27857408 kB",
            "SwapCached": "0 kB",
            "Active": "6666752 kB",
            "Inactive": "27387328 kB",
            "Active(anon)": "5792192 kB",
            "Inactive(anon)": "0 kB",
            "Active(file)": "874560 kB",
            "Inactive(file)": "27387328 kB",
            "Unevictable": "3072 kB",
            "Mlocked": "0 kB",
            "SwapTotal": "0 kB",
            "SwapFree": "0 kB",
            "Zswap": "0 kB",
            "Zswapped": "0 kB",
            "Dirty": "0 kB",
            "Writeback": "0 kB",
            "AnonPages": "5552832 kB",
            "Mapped": "647424 kB",
            "Shmem": "242752 kB",
            "KReclaimable": "564416 kB",
            "Slab": "5242496 kB",
            "SReclaimable": "564416 kB",
            "SUnreclaim": "4678080 kB",
            "KernelStack": "247744 kB",
            "PageTables": "47168 kB",
            "SecPageTables": "0 kB",
            "NFS_Unstable": "0 kB",
            "Bounce": "0 kB",
            "WritebackTmp": "0 kB",
            "CommitLimit": "449441664 kB",
            "Committed_AS": "31079616 kB",
            "VmallocTotal": "137168158720 kB",
            "VmallocUsed": "829120 kB",
            "VmallocChunk": "0 kB",
            "Percpu": "1640448 kB",
            "HardwareCorrupted": "0 kB",
            "AnonHugePages": "0 kB",
            "ShmemHugePages": "0 kB",
            "ShmemPmdMapped": "0 kB",
            "FileHugePages": "0 kB",
            "FilePmdMapped": "0 kB",
            "CmaTotal": "0 kB",
            "CmaFree": "0 kB",
            "HugePages_Total": "0",
            "HugePages_Free": "0",
            "HugePages_Rsvd": "0",
            "HugePages_Surp": "0",
            "Hugepagesize": "524288 kB",
            "Hugetlb": "0 kB"
        },
        "end": "2025-11-30T18:45:49.033689"
    },
    "5": {
        "load": {
            "block1": [
                4.2864484786987305,
                0.02008342742919922,
                0.0011386871337890625,
                0.0011544227600097656,
                0.8902747631072998,
                0.0007531642913818359
            ],
            "eval": []
        },
        "proc": {
            "block1": [
                4.609872341156006,
                0.34349894523620605,
                0.32451891899108887,
                0.32453227043151855,
                1.2136681079864502,
                0.32410717010498047
            ],
            "eval": []
        },
        "throughput": {
            "block1": 10.345818031385466,
            "eval": 0.0
        },
        "au": {
            "block1": 59.73756234420555,
            "eval": 0.0
        },
        "compute": {
            "block1": [
                0.3233602046966553,
                0.32335948944091797,
                0.3233504295349121,
                0.3233518600463867,
                0.3233489990234375,
                0.3233311176300049
            ],
            "eval": []
        },
        "host_meminfo": {
            "MemTotal": "898883328 kB",
            "MemFree": "845784256 kB",
            "MemAvailable": "822263808 kB",
            "Buffers": "647232 kB",
            "Cached": "27869952 kB",
            "SwapCached": "0 kB",
            "Active": "6688128 kB",
            "Inactive": "27387328 kB",
            "Active(anon)": "5813568 kB",
            "Inactive(anon)": "0 kB",
            "Active(file)": "874560 kB",
            "Inactive(file)": "27387328 kB",
            "Unevictable": "3072 kB",
            "Mlocked": "0 kB",
            "SwapTotal": "0 kB",
            "SwapFree": "0 kB",
            "Zswap": "0 kB",
            "Zswapped": "0 kB",
            "Dirty": "64 kB",
            "Writeback": "0 kB",
            "AnonPages": "5561344 kB",
            "Mapped": "647424 kB",
            "Shmem": "255296 kB",
            "KReclaimable": "564416 kB",
            "Slab": "5242496 kB",
            "SReclaimable": "564416 kB",
            "SUnreclaim": "4678080 kB",
            "KernelStack": "247744 kB",
            "PageTables": "47168 kB",
            "SecPageTables": "0 kB",
            "NFS_Unstable": "0 kB",
            "Bounce": "0 kB",
            "WritebackTmp": "0 kB",
            "CommitLimit": "449441664 kB",
            "Committed_AS": "31079616 kB",
            "VmallocTotal": "137168158720 kB",
            "VmallocUsed": "829120 kB",
            "VmallocChunk": "0 kB",
            "Percpu": "1640448 kB",
            "HardwareCorrupted": "0 kB",
            "AnonHugePages": "0 kB",
            "ShmemHugePages": "0 kB",
            "ShmemPmdMapped": "0 kB",
            "FileHugePages": "0 kB",
            "FilePmdMapped": "0 kB",
            "CmaTotal": "0 kB",
            "CmaFree": "0 kB",
            "HugePages_Total": "0",
            "HugePages_Free": "0",
            "HugePages_Rsvd": "0",
            "HugePages_Surp": "0",
            "Hugepagesize": "524288 kB",
            "Hugetlb": "0 kB"
        },
        "end": "2025-11-30T18:45:56.360798"
    },
    "hostname": "sdumont2nd3007"
}