{
    "host_memory_GB": 857.241943359375,
    "host_cpu_count": 288,
    "host_processor_name": "aarch64",
    "potential_caching": 1,
    "host_cpuinfo": {
        "BogoMIPS": "2000.00",
        "Features": "fp asimd evtstrm aes pmull sha1 sha2 crc32 atomics fphp asimdhp cpuid asimdrdm jscvt fcma lrcpc dcpop sha3 sm3 sm4 asimddp sha512 sve asimdfhm dit uscat ilrcpc flagm ssbs sb dcpodp sve2 sveaes svepmull svebitperm svesha3 svesm4 flagm2 frint svei8mm svebf16 i8mm bf16 dgh",
        "CPU implementer": "0x41",
        "CPU architecture": "8",
        "CPU variant": "0x0",
        "CPU part": "0xd4f",
        "CPU revision": "0"
    },
    "host_meminfo": {
        "MemTotal": "898883328 kB",
        "MemFree": "822846336 kB",
        "MemAvailable": "811685248 kB",
        "Buffers": "647424 kB",
        "Cached": "52546176 kB",
        "SwapCached": "0 kB",
        "Active": "5054720 kB",
        "Inactive": "52099072 kB",
        "Active(anon)": "4180160 kB",
        "Inactive(anon)": "0 kB",
        "Active(file)": "874560 kB",
        "Inactive(file)": "52099072 kB",
        "Unevictable": "3072 kB",
        "Mlocked": "0 kB",
        "SwapTotal": "0 kB",
        "SwapFree": "0 kB",
        "Zswap": "0 kB",
        "Zswapped": "0 kB",
        "Dirty": "15744 kB",
        "Writeback": "0 kB",
        "AnonPages": "3965696 kB",
        "Mapped": "634240 kB",
        "Shmem": "219968 kB",
        "KReclaimable": "571392 kB",
        "Slab": "5342144 kB",
        "SReclaimable": "571392 kB",
        "SUnreclaim": "4770752 kB",
        "KernelStack": "241152 kB",
        "PageTables": "25344 kB",
        "SecPageTables": "0 kB",
        "NFS_Unstable": "0 kB",
        "Bounce": "0 kB",
        "WritebackTmp": "0 kB",
        "CommitLimit": "449441664 kB",
        "Committed_AS": "8416512 kB",
        "VmallocTotal": "137168158720 kB",
        "VmallocUsed": "823040 kB",
        "VmallocChunk": "0 kB",
        "Percpu": "1640448 kB",
        "HardwareCorrupted": "0 kB",
        "AnonHugePages": "0 kB",
        "ShmemHugePages": "0 kB",
        "ShmemPmdMapped": "0 kB",
        "FileHugePages": "0 kB",
        "FilePmdMapped": "0 kB",
        "CmaTotal": "0 kB",
        "CmaFree": "0 kB",
        "HugePages_Total": "0",
        "HugePages_Free": "0",
        "HugePages_Rsvd": "0",
        "HugePages_Surp": "0",
        "Hugepagesize": "524288 kB",
        "Hugetlb": "0 kB"
    },
    "1": {
        "load": {
            "block1": [
                11.864980220794678,
                0.03815126419067383,
                0.00029277801513671875,
                0.0003676414489746094,
                3.922785520553589,
                0.0008897781372070312
            ],
            "eval": []
        },
        "proc": {
            "block1": [
                12.188447713851929,
                0.3615548610687256,
                0.32367682456970215,
                0.3237473964691162,
                4.246190309524536,
                0.32425713539123535
            ],
            "eval": []
        },
        "throughput": {
            "block1": 3.5110163337483913,
            "eval": 0.0
        },
        "au": {
            "block1": 20.273148943994094,
            "eval": 0.0
        },
        "compute": {
            "block1": [
                0.3233642578125,
                0.32335686683654785,
                0.32335400581359863,
                0.32335615158081055,
                0.3233609199523926,
                0.3233351707458496
            ],
            "eval": []
        },
        "host_meminfo": {
            "MemTotal": "898883328 kB",
            "MemFree": "822814080 kB",
            "MemAvailable": "811652992 kB",
            "Buffers": "647424 kB",
            "Cached": "52546176 kB",
            "SwapCached": "0 kB",
            "Active": "5086976 kB",
            "Inactive": "52099072 kB",
            "Active(anon)": "4212416 kB",
            "Inactive(anon)": "0 kB",
            "Active(file)": "874560 kB",
            "Inactive(file)": "52099072 kB",
            "Unevictable": "3072 kB",
            "Mlocked": "0 kB",
            "SwapTotal": "0 kB",
            "SwapFree": "0 kB",
            "Zswap": "0 kB",
            "Zswapped": "0 kB",
            "Dirty": "15744 kB",
            "Writeback": "0 kB",
            "AnonPages": "3997952 kB",
            "Mapped": "634240 kB",
            "Shmem": "219968 kB",
            "KReclaimable": "571392 kB",
            "Slab": "5342144 kB",
            "SReclaimable": "571392 kB",
            "SUnreclaim": "4770752 kB",
            "KernelStack": "241152 kB",
            "PageTables": "25344 kB",
            "SecPageTables": "0 kB",
            "NFS_Unstable": "0 kB",
            "Bounce": "0 kB",
            "WritebackTmp": "0 kB",
            "CommitLimit": "449441664 kB",
            "Committed_AS": "8453440 kB",
            "VmallocTotal": "137168158720 kB",
            "VmallocUsed": "823040 kB",
            "VmallocChunk": "0 kB",
            "Percpu": "1640448 kB",
            "HardwareCorrupted": "0 kB",
            "AnonHugePages": "0 kB",
            "ShmemHugePages": "0 kB",
            "ShmemPmdMapped": "0 kB",
            "FileHugePages": "0 kB",
            "FilePmdMapped": "0 kB",
            "CmaTotal": "0 kB",
            "CmaFree": "0 kB",
            "HugePages_Total": "0",
            "HugePages_Free": "0",
            "HugePages_Rsvd": "0",
            "HugePages_Surp": "0",
            "Hugepagesize": "524288 kB",
            "Hugetlb": "0 kB"
        },
        "end": "2025-11-30T18:50:36.511890"
    },
    "2": {
        "load": {
            "block1": [
                11.656816720962524,
                0.037427425384521484,
                0.00031685829162597656,
                0.0003573894500732422,
                3.832129955291748,
                0.0009243488311767578
            ],
            "eval": []
        },
        "proc": {
            "block1": [
                11.980236053466797,
                0.3608250617980957,
                0.32372069358825684,
                0.3237419128417969,
                4.155534982681274,
                0.32428979873657227
            ],
            "eval": []
        },
        "throughput": {
            "block1": 3.4627522090502514,
            "eval": 0.0
        },
        "au": {
            "block1": 19.994443816574357,
            "eval": 0.0
        },
        "compute": {
            "block1": [
                0.3233678340911865,
                0.32335662841796875,
                0.32335805892944336,
                0.32335591316223145,
                0.32335734367370605,
                0.3233335018157959
            ],
            "eval": []
        },
        "host_meminfo": {
            "MemTotal": "898883328 kB",
            "MemFree": "821449664 kB",
            "MemAvailable": "810288768 kB",
            "Buffers": "647680 kB",
            "Cached": "52574016 kB",
            "SwapCached": "0 kB",
            "Active": "6419328 kB",
            "Inactive": "52099456 kB",
            "Active(anon)": "5544768 kB",
            "Inactive(anon)": "0 kB",
            "Active(file)": "874560 kB",
            "Inactive(file)": "52099456 kB",
            "Unevictable": "3072 kB",
            "Mlocked": "0 kB",
            "SwapTotal": "0 kB",
            "SwapFree": "0 kB",
            "Zswap": "0 kB",
            "Zswapped": "0 kB",
            "Dirty": "16320 kB",
            "Writeback": "0 kB",
            "AnonPages": "5316416 kB",
            "Mapped": "643328 kB",
            "Shmem": "247616 kB",
            "KReclaimable": "571392 kB",
            "Slab": "5350528 kB",
            "SReclaimable": "571392 kB",
            "SUnreclaim": "4779136 kB",
            "KernelStack": "246400 kB",
            "PageTables": "36736 kB",
            "SecPageTables": "0 kB",
            "NFS_Unstable": "0 kB",
            "Bounce": "0 kB",
            "WritebackTmp": "0 kB",
            "CommitLimit": "449441664 kB",
            "Committed_AS": "30896192 kB",
            "VmallocTotal": "137168158720 kB",
            "VmallocUsed": "827840 kB",
            "VmallocChunk": "0 kB",
            "Percpu": "1640448 kB",
            "HardwareCorrupted": "0 kB",
            "AnonHugePages": "0 kB",
            "ShmemHugePages": "0 kB",
            "ShmemPmdMapped": "0 kB",
            "FileHugePages": "0 kB",
            "FilePmdMapped": "0 kB",
            "CmaTotal": "0 kB",
            "CmaFree": "0 kB",
            "HugePages_Total": "0",
            "HugePages_Free": "0",
            "HugePages_Rsvd": "0",
            "HugePages_Surp": "0",
            "Hugepagesize": "524288 kB",
            "Hugetlb": "0 kB"
        },
        "end": "2025-11-30T18:50:56.585733"
    },
    "3": {
        "load": {
            "block1": [
                11.684650659561157,
                0.027400970458984375,
                0.00030422210693359375,
                0.00035119056701660156,
                3.789454936981201,
                0.0009710788726806641
            ],
            "eval": []
        },
        "proc": {
            "block1": [
                12.008055210113525,
                0.35080718994140625,
                0.32372140884399414,
                0.32377004623413086,
                4.112855911254883,
                0.3243398666381836
            ],
            "eval": []
        },
        "throughput": {
            "block1": 3.4520180402428773,
            "eval": 0.0
        },
        "au": {
            "block1": 19.932536621389694,
            "eval": 0.0
        },
        "compute": {
            "block1": [
                0.32335972785949707,
                0.32335829734802246,
                0.3233606815338135,
                0.32335782051086426,
                0.32335686683654785,
                0.323333740234375
            ],
            "eval": []
        },
        "host_meminfo": {
            "MemTotal": "898883328 kB",
            "MemFree": "820899712 kB",
            "MemAvailable": "809738816 kB",
            "Buffers": "647680 kB",
            "Cached": "52580160 kB",
            "SwapCached": "0 kB",
            "Active": "6791616 kB",
            "Inactive": "52099520 kB",
            "Active(anon)": "5917056 kB",
            "Inactive(anon)": "0 kB",
            "Active(file)": "874560 kB",
            "Inactive(file)": "52099520 kB",
            "Unevictable": "3072 kB",
            "Mlocked": "0 kB",
            "SwapTotal": "0 kB",
            "SwapFree": "0 kB",
            "Zswap": "0 kB",
            "Zswapped": "0 kB",
            "Dirty": "128 kB",
            "Writeback": "0 kB",
            "AnonPages": "5666368 kB",
            "Mapped": "644608 kB",
            "Shmem": "253760 kB",
            "KReclaimable": "571392 kB",
            "Slab": "5361024 kB",
            "SReclaimable": "571392 kB",
            "SUnreclaim": "4789632 kB",
            "KernelStack": "248448 kB",
            "PageTables": "48448 kB",
            "SecPageTables": "0 kB",
            "NFS_Unstable": "0 kB",
            "Bounce": "0 kB",
            "WritebackTmp": "0 kB",
            "CommitLimit": "449441664 kB",
            "Committed_AS": "31109440 kB",
            "VmallocTotal": "137168158720 kB",
            "VmallocUsed": "829888 kB",
            "VmallocChunk": "0 kB",
            "Percpu": "1640448 kB",
            "HardwareCorrupted": "0 kB",
            "AnonHugePages": "0 kB",
            "ShmemHugePages": "0 kB",
            "ShmemPmdMapped": "0 kB",
            "FileHugePages": "0 kB",
            "FilePmdMapped": "0 kB",
            "CmaTotal": "0 kB",
            "CmaFree": "0 kB",
            "HugePages_Total": "0",
            "HugePages_Free": "0",
            "HugePages_Rsvd": "0",
            "HugePages_Surp": "0",
            "Hugepagesize": "524288 kB",
            "Hugetlb": "0 kB"
        },
        "end": "2025-11-30T18:51:16.710341"
    },
    "4": {
        "load": {
            "block1": [
                11.699277639389038,
                0.020052433013916016,
                0.0002841949462890625,
                0.0003509521484375,
                3.7333896160125732,
                0.0009894371032714844
            ],
            "eval": []
        },
        "proc": {
            "block1": [
                12.02268671989441,
                0.3434634208679199,
                0.3236832618713379,
                0.3237276077270508,
                4.056792736053467,
                0.32436108589172363
            ],
            "eval": []
        },
        "throughput": {
            "block1": 3.498349685157348,
            "eval": 0.0
        },
        "au": {
            "block1": 20.200057425826984,
            "eval": 0.0
        },
        "compute": {
            "block1": [
                0.3233633041381836,
                0.32335925102233887,
                0.32335925102233887,
                0.32335543632507324,
                0.32335758209228516,
                0.3233354091644287
            ],
            "eval": []
        },
        "host_meminfo": {
            "MemTotal": "898883328 kB",
            "MemFree": "820863808 kB",
            "MemAvailable": "809702976 kB",
            "Buffers": "647744 kB",
            "Cached": "52580160 kB",
            "SwapCached": "0 kB",
            "Active": "6847232 kB",
            "Inactive": "52099584 kB",
            "Active(anon)": "5972672 kB",
            "Inactive(anon)": "0 kB",
            "Active(file)": "874560 kB",
            "Inactive(file)": "52099584 kB",
            "Unevictable": "3072 kB",
            "Mlocked": "0 kB",
            "SwapTotal": "0 kB",
            "SwapFree": "0 kB",
            "Zswap": "0 kB",
            "Zswapped": "0 kB",
            "Dirty": "64 kB",
            "Writeback": "0 kB",
            "AnonPages": "5721984 kB",
            "Mapped": "647424 kB",
            "Shmem": "253760 kB",
            "KReclaimable": "571392 kB",
            "Slab": "5360192 kB",
            "SReclaimable": "571392 kB",
            "SUnreclaim": "4788800 kB",
            "KernelStack": "247872 kB",
            "PageTables": "48576 kB",
            "SecPageTables": "0 kB",
            "NFS_Unstable": "0 kB",
            "Bounce": "0 kB",
            "WritebackTmp": "0 kB",
            "CommitLimit": "449441664 kB",
            "Committed_AS": "31125824 kB",
            "VmallocTotal": "137168158720 kB",
            "VmallocUsed": "829376 kB",
            "VmallocChunk": "0 kB",
            "Percpu": "1640448 kB",
            "HardwareCorrupted": "0 kB",
            "AnonHugePages": "0 kB",
            "ShmemHugePages": "0 kB",
            "ShmemPmdMapped": "0 kB",
            "FileHugePages": "0 kB",
            "FilePmdMapped": "0 kB",
            "CmaTotal": "0 kB",
            "CmaFree": "0 kB",
            "HugePages_Total": "0",
            "HugePages_Free": "0",
            "HugePages_Rsvd": "0",
            "HugePages_Surp": "0",
            "Hugepagesize": "524288 kB",
            "Hugetlb": "0 kB"
        },
        "end": "2025-11-30T18:51:36.741958"
    },
    "5": {
        "load": {
            "block1": [
                11.77756142616272,
                0.019910335540771484,
                0.0003285408020019531,
                0.00035834312438964844,
                3.7419769763946533,
                0.0009527206420898438
            ],
            "eval": []
        },
        "proc": {
            "block1": [
                12.10096526145935,
                0.3433218002319336,
                0.323718786239624,
                0.3237440586090088,
                4.0653791427612305,
                0.3243215084075928
            ],
            "eval": []
        },
        "throughput": {
            "block1": 3.5226266586328094,
            "eval": 0.0
        },
        "au": {
            "block1": 20.340134756679465,
            "eval": 0.0
        },
        "compute": {
            "block1": [
                0.32335829734802246,
                0.32335805892944336,
                0.32335638999938965,
                0.32335472106933594,
                0.32335519790649414,
                0.3233344554901123
            ],
            "eval": []
        },
        "host_meminfo": {
            "MemTotal": "898883328 kB",
            "MemFree": "820853376 kB",
            "MemAvailable": "809692544 kB",
            "Buffers": "647744 kB",
            "Cached": "52580160 kB",
            "SwapCached": "0 kB",
            "Active": "6855168 kB",
            "Inactive": "52099584 kB",
            "Active(anon)": "5980608 kB",
            "Inactive(anon)": "0 kB",
            "Active(file)": "874560 kB",
            "Inactive(file)": "52099584 kB",
            "Unevictable": "3072 kB",
            "Mlocked": "0 kB",
            "SwapTotal": "0 kB",
            "SwapFree": "0 kB",
            "Zswap": "0 kB",
            "Zswapped": "0 kB",
            "Dirty": "0 kB",
            "Writeback": "64 kB",
            "AnonPages": "5729920 kB",
            "Mapped": "647424 kB",
            "Shmem": "253760 kB",
            "KReclaimable": "571392 kB",
            "Slab": "5360192 kB",
            "SReclaimable": "571392 kB",
            "SUnreclaim": "4788800 kB",
            "KernelStack": "247936 kB",
            "PageTables": "48576 kB",
            "SecPageTables": "0 kB",
            "NFS_Unstable": "0 kB",
            "Bounce": "0 kB",
            "WritebackTmp": "0 kB",
            "CommitLimit": "449441664 kB",
            "Committed_AS": "31125824 kB",
            "VmallocTotal": "137168158720 kB",
            "VmallocUsed": "829376 kB",
            "VmallocChunk": "0 kB",
            "Percpu": "1640448 kB",
            "HardwareCorrupted": "0 kB",
            "AnonHugePages": "0 kB",
            "ShmemHugePages": "0 kB",
            "ShmemPmdMapped": "0 kB",
            "FileHugePages": "0 kB",
            "FilePmdMapped": "0 kB",
            "CmaTotal": "0 kB",
            "CmaFree": "0 kB",
            "HugePages_Total": "0",
            "HugePages_Free": "0",
            "HugePages_Rsvd": "0",
            "HugePages_Surp": "0",
            "Hugepagesize": "524288 kB",
            "Hugetlb": "0 kB"
        },
        "end": "2025-11-30T18:51:56.801793"
    },
    "hostname": "sdumont2nd3007"
}