{
    "host_memory_GB": 857.241943359375,
    "host_cpu_count": 288,
    "host_processor_name": "aarch64",
    "potential_caching": 1,
    "host_cpuinfo": {
        "BogoMIPS": "2000.00",
        "Features": "fp asimd evtstrm aes pmull sha1 sha2 crc32 atomics fphp asimdhp cpuid asimdrdm jscvt fcma lrcpc dcpop sha3 sm3 sm4 asimddp sha512 sve asimdfhm dit uscat ilrcpc flagm ssbs sb dcpodp sve2 sveaes svepmull svebitperm svesha3 svesm4 flagm2 frint svei8mm svebf16 i8mm bf16 dgh",
        "CPU implementer": "0x41",
        "CPU architecture": "8",
        "CPU variant": "0x0",
        "CPU part": "0xd4f",
        "CPU revision": "0"
    },
    "host_meminfo": {
        "MemTotal": "898883328 kB",
        "MemFree": "840769792 kB",
        "MemAvailable": "817680192 kB",
        "Buffers": "1162304 kB",
        "Cached": "28085440 kB",
        "SwapCached": "0 kB",
        "Active": "7528256 kB",
        "Inactive": "28123328 kB",
        "Active(anon)": "6697728 kB",
        "Inactive(anon)": "320 kB",
        "Active(file)": "830528 kB",
        "Inactive(file)": "28123008 kB",
        "Unevictable": "3072 kB",
        "Mlocked": "0 kB",
        "SwapTotal": "0 kB",
        "SwapFree": "0 kB",
        "Zswap": "0 kB",
        "Zswapped": "0 kB",
        "Dirty": "576 kB",
        "Writeback": "0 kB",
        "AnonPages": "6411840 kB",
        "Mapped": "679808 kB",
        "Shmem": "294208 kB",
        "KReclaimable": "734464 kB",
        "Slab": "6952768 kB",
        "SReclaimable": "734464 kB",
        "SUnreclaim": "6218304 kB",
        "KernelStack": "238656 kB",
        "PageTables": "21632 kB",
        "SecPageTables": "0 kB",
        "NFS_Unstable": "0 kB",
        "Bounce": "0 kB",
        "WritebackTmp": "0 kB",
        "CommitLimit": "449441664 kB",
        "Committed_AS": "12082240 kB",
        "VmallocTotal": "137168158720 kB",
        "VmallocUsed": "820800 kB",
        "VmallocChunk": "0 kB",
        "Percpu": "1677312 kB",
        "HardwareCorrupted": "0 kB",
        "AnonHugePages": "0 kB",
        "ShmemHugePages": "0 kB",
        "ShmemPmdMapped": "0 kB",
        "FileHugePages": "0 kB",
        "FilePmdMapped": "0 kB",
        "CmaTotal": "0 kB",
        "CmaFree": "0 kB",
        "HugePages_Total": "0",
        "HugePages_Free": "0",
        "HugePages_Rsvd": "0",
        "HugePages_Surp": "0",
        "Hugepagesize": "524288 kB",
        "Hugetlb": "0 kB"
    },
    "1": {
        "load": {
            "block1": [
                3.673312187194824,
                0.00023412704467773438,
                0.0001735687255859375
            ],
            "eval": []
        },
        "proc": {
            "block1": [
                3.9967617988586426,
                0.32358407974243164,
                0.3235175609588623
            ],
            "eval": []
        },
        "throughput": {
            "block1": 10.784823145833975,
            "eval": 0.0
        },
        "au": {
            "block1": 99.6304304066037,
            "eval": 0.0
        },
        "compute": {
            "block1": [
                0.3233499526977539,
                0.3233315944671631,
                0.3233299255371094
            ],
            "eval": []
        },
        "host_meminfo": {
            "MemTotal": "898883328 kB",
            "MemFree": "840705280 kB",
            "MemAvailable": "817615680 kB",
            "Buffers": "1162304 kB",
            "Cached": "28085440 kB",
            "SwapCached": "0 kB",
            "Active": "7592768 kB",
            "Inactive": "28123328 kB",
            "Active(anon)": "6762240 kB",
            "Inactive(anon)": "320 kB",
            "Active(file)": "830528 kB",
            "Inactive(file)": "28123008 kB",
            "Unevictable": "3072 kB",
            "Mlocked": "0 kB",
            "SwapTotal": "0 kB",
            "SwapFree": "0 kB",
            "Zswap": "0 kB",
            "Zswapped": "0 kB",
            "Dirty": "576 kB",
            "Writeback": "0 kB",
            "AnonPages": "6476352 kB",
            "Mapped": "679808 kB",
            "Shmem": "294208 kB",
            "KReclaimable": "734464 kB",
            "Slab": "6952768 kB",
            "SReclaimable": "734464 kB",
            "SUnreclaim": "6218304 kB",
            "KernelStack": "238656 kB",
            "PageTables": "21632 kB",
            "SecPageTables": "0 kB",
            "NFS_Unstable": "0 kB",
            "Bounce": "0 kB",
            "WritebackTmp": "0 kB",
            "CommitLimit": "449441664 kB",
            "Committed_AS": "12155968 kB",
            "VmallocTotal": "137168158720 kB",
            "VmallocUsed": "820800 kB",
            "VmallocChunk": "0 kB",
            "Percpu": "1677312 kB",
            "HardwareCorrupted": "0 kB",
            "AnonHugePages": "0 kB",
            "ShmemHugePages": "0 kB",
            "ShmemPmdMapped": "0 kB",
            "FileHugePages": "0 kB",
            "FilePmdMapped": "0 kB",
            "CmaTotal": "0 kB",
            "CmaFree": "0 kB",
            "HugePages_Total": "0",
            "HugePages_Free": "0",
            "HugePages_Rsvd": "0",
            "HugePages_Surp": "0",
            "Hugepagesize": "524288 kB",
            "Hugetlb": "0 kB"
        },
        "end": "2025-10-07T11:24:44.754582"
    },
    "2": {
        "load": {
            "block1": [
                3.446133613586426,
                0.0002453327178955078,
                0.00017404556274414062
            ],
            "eval": []
        },
        "proc": {
            "block1": [
                3.7695462703704834,
                0.3235921859741211,
                0.3235185146331787
            ],
            "eval": []
        },
        "throughput": {
            "block1": 10.791609633601455,
            "eval": 0.0
        },
        "au": {
            "block1": 99.69367546801419,
            "eval": 0.0
        },
        "compute": {
            "block1": [
                0.32335424423217773,
                0.3233318328857422,
                0.3233332633972168
            ],
            "eval": []
        },
        "host_meminfo": {
            "MemTotal": "898883328 kB",
            "MemFree": "838316864 kB",
            "MemAvailable": "815227392 kB",
            "Buffers": "1162368 kB",
            "Cached": "28118528 kB",
            "SwapCached": "0 kB",
            "Active": "9913024 kB",
            "Inactive": "28123456 kB",
            "Active(anon)": "9082496 kB",
            "Inactive(anon)": "320 kB",
            "Active(file)": "830528 kB",
            "Inactive(file)": "28123136 kB",
            "Unevictable": "3072 kB",
            "Mlocked": "0 kB",
            "SwapTotal": "0 kB",
            "SwapFree": "0 kB",
            "Zswap": "0 kB",
            "Zswapped": "0 kB",
            "Dirty": "320 kB",
            "Writeback": "0 kB",
            "AnonPages": "8776704 kB",
            "Mapped": "692992 kB",
            "Shmem": "327232 kB",
            "KReclaimable": "734528 kB",
            "Slab": "6981248 kB",
            "SReclaimable": "734528 kB",
            "SUnreclaim": "6246720 kB",
            "KernelStack": "247360 kB",
            "PageTables": "61184 kB",
            "SecPageTables": "0 kB",
            "NFS_Unstable": "0 kB",
            "Bounce": "0 kB",
            "WritebackTmp": "0 kB",
            "CommitLimit": "449441664 kB",
            "Committed_AS": "71572800 kB",
            "VmallocTotal": "137168158720 kB",
            "VmallocUsed": "829312 kB",
            "VmallocChunk": "0 kB",
            "Percpu": "1677312 kB",
            "HardwareCorrupted": "0 kB",
            "AnonHugePages": "0 kB",
            "ShmemHugePages": "0 kB",
            "ShmemPmdMapped": "0 kB",
            "FileHugePages": "0 kB",
            "FilePmdMapped": "0 kB",
            "CmaTotal": "0 kB",
            "CmaFree": "0 kB",
            "HugePages_Total": "0",
            "HugePages_Free": "0",
            "HugePages_Rsvd": "0",
            "HugePages_Surp": "0",
            "Hugepagesize": "524288 kB",
            "Hugetlb": "0 kB"
        },
        "end": "2025-10-07T11:24:49.179997"
    },
    "3": {
        "load": {
            "block1": [
                3.3869388103485107,
                0.00022101402282714844,
                0.00018978118896484375
            ],
            "eval": []
        },
        "proc": {
            "block1": [
                3.710341453552246,
                0.32356786727905273,
                0.3235321044921875
            ],
            "eval": []
        },
        "throughput": {
            "block1": 10.791554101985623,
            "eval": 0.0
        },
        "au": {
            "block1": 99.69264788150514,
            "eval": 0.0
        },
        "compute": {
            "block1": [
                0.323345422744751,
                0.3233320713043213,
                0.3233296871185303
            ],
            "eval": []
        },
        "host_meminfo": {
            "MemTotal": "898883328 kB",
            "MemFree": "837322368 kB",
            "MemAvailable": "814232896 kB",
            "Buffers": "1162368 kB",
            "Cached": "28160256 kB",
            "SwapCached": "0 kB",
            "Active": "10561920 kB",
            "Inactive": "28123456 kB",
            "Active(anon)": "9731392 kB",
            "Inactive(anon)": "320 kB",
            "Active(file)": "830528 kB",
            "Inactive(file)": "28123136 kB",
            "Unevictable": "3072 kB",
            "Mlocked": "0 kB",
            "SwapTotal": "0 kB",
            "SwapFree": "0 kB",
            "Zswap": "0 kB",
            "Zswapped": "0 kB",
            "Dirty": "896 kB",
            "Writeback": "0 kB",
            "AnonPages": "9365824 kB",
            "Mapped": "696064 kB",
            "Shmem": "368960 kB",
            "KReclaimable": "734528 kB",
            "Slab": "6989952 kB",
            "SReclaimable": "734528 kB",
            "SUnreclaim": "6255424 kB",
            "KernelStack": "252480 kB",
            "PageTables": "70208 kB",
            "SecPageTables": "0 kB",
            "NFS_Unstable": "0 kB",
            "Bounce": "0 kB",
            "WritebackTmp": "0 kB",
            "CommitLimit": "449441664 kB",
            "Committed_AS": "71749952 kB",
            "VmallocTotal": "137168158720 kB",
            "VmallocUsed": "834112 kB",
            "VmallocChunk": "0 kB",
            "Percpu": "1677312 kB",
            "HardwareCorrupted": "0 kB",
            "AnonHugePages": "0 kB",
            "ShmemHugePages": "0 kB",
            "ShmemPmdMapped": "0 kB",
            "FileHugePages": "0 kB",
            "FilePmdMapped": "0 kB",
            "CmaTotal": "0 kB",
            "CmaFree": "0 kB",
            "HugePages_Total": "0",
            "HugePages_Free": "0",
            "HugePages_Rsvd": "0",
            "HugePages_Surp": "0",
            "Hugepagesize": "524288 kB",
            "Hugetlb": "0 kB"
        },
        "end": "2025-10-07T11:24:53.544306"
    },
    "4": {
        "load": {
            "block1": [
                3.3878376483917236,
                0.00021696090698242188,
                0.00018167495727539062
            ],
            "eval": []
        },
        "proc": {
            "block1": [
                3.7112348079681396,
                0.323561429977417,
                0.32352614402770996
            ],
            "eval": []
        },
        "throughput": {
            "block1": 10.791891267023528,
            "eval": 0.0
        },
        "au": {
            "block1": 99.69598316237057,
            "eval": 0.0
        },
        "compute": {
            "block1": [
                0.32334065437316895,
                0.3233304023742676,
                0.3233327865600586
            ],
            "eval": []
        },
        "host_meminfo": {
            "MemTotal": "898883328 kB",
            "MemFree": "837263296 kB",
            "MemAvailable": "814173824 kB",
            "Buffers": "1162368 kB",
            "Cached": "28153088 kB",
            "SwapCached": "0 kB",
            "Active": "10600000 kB",
            "Inactive": "28123456 kB",
            "Active(anon)": "9769472 kB",
            "Inactive(anon)": "320 kB",
            "Active(file)": "830528 kB",
            "Inactive(file)": "28123136 kB",
            "Unevictable": "3072 kB",
            "Mlocked": "0 kB",
            "SwapTotal": "0 kB",
            "SwapFree": "0 kB",
            "Zswap": "0 kB",
            "Zswapped": "0 kB",
            "Dirty": "896 kB",
            "Writeback": "0 kB",
            "AnonPages": "9411072 kB",
            "Mapped": "701696 kB",
            "Shmem": "361792 kB",
            "KReclaimable": "734528 kB",
            "Slab": "6990144 kB",
            "SReclaimable": "734528 kB",
            "SUnreclaim": "6255616 kB",
            "KernelStack": "252480 kB",
            "PageTables": "70528 kB",
            "SecPageTables": "0 kB",
            "NFS_Unstable": "0 kB",
            "Bounce": "0 kB",
            "WritebackTmp": "0 kB",
            "CommitLimit": "449441664 kB",
            "Committed_AS": "71749952 kB",
            "VmallocTotal": "137168158720 kB",
            "VmallocUsed": "834112 kB",
            "VmallocChunk": "0 kB",
            "Percpu": "1677312 kB",
            "HardwareCorrupted": "0 kB",
            "AnonHugePages": "0 kB",
            "ShmemHugePages": "0 kB",
            "ShmemPmdMapped": "0 kB",
            "FileHugePages": "0 kB",
            "FilePmdMapped": "0 kB",
            "CmaTotal": "0 kB",
            "CmaFree": "0 kB",
            "HugePages_Total": "0",
            "HugePages_Free": "0",
            "HugePages_Rsvd": "0",
            "HugePages_Surp": "0",
            "Hugepagesize": "524288 kB",
            "Hugetlb": "0 kB"
        },
        "end": "2025-10-07T11:24:57.909475"
    },
    "5": {
        "load": {
            "block1": [
                3.3926382064819336,
                0.00021958351135253906,
                0.00019311904907226562
            ],
            "eval": []
        },
        "proc": {
            "block1": [
                3.7160422801971436,
                0.3235657215118408,
                0.32354068756103516
            ],
            "eval": []
        },
        "throughput": {
            "block1": 10.76383601499305,
            "eval": 0.0
        },
        "au": {
            "block1": 99.43717408009198,
            "eval": 0.0
        },
        "compute": {
            "block1": [
                0.3233449459075928,
                0.3233315944671631,
                0.3233339786529541
            ],
            "eval": []
        },
        "host_meminfo": {
            "MemTotal": "898883328 kB",
            "MemFree": "837251584 kB",
            "MemAvailable": "814162112 kB",
            "Buffers": "1162368 kB",
            "Cached": "28160256 kB",
            "SwapCached": "0 kB",
            "Active": "10619072 kB",
            "Inactive": "28123456 kB",
            "Active(anon)": "9788544 kB",
            "Inactive(anon)": "320 kB",
            "Active(file)": "830528 kB",
            "Inactive(file)": "28123136 kB",
            "Unevictable": "3072 kB",
            "Mlocked": "0 kB",
            "SwapTotal": "0 kB",
            "SwapFree": "0 kB",
            "Zswap": "0 kB",
            "Zswapped": "0 kB",
            "Dirty": "448 kB",
            "Writeback": "0 kB",
            "AnonPages": "9422976 kB",
            "Mapped": "701696 kB",
            "Shmem": "368960 kB",
            "KReclaimable": "734528 kB",
            "Slab": "6990144 kB",
            "SReclaimable": "734528 kB",
            "SUnreclaim": "6255616 kB",
            "KernelStack": "252480 kB",
            "PageTables": "70528 kB",
            "SecPageTables": "0 kB",
            "NFS_Unstable": "0 kB",
            "Bounce": "0 kB",
            "WritebackTmp": "0 kB",
            "CommitLimit": "449441664 kB",
            "Committed_AS": "71750208 kB",
            "VmallocTotal": "137168158720 kB",
            "VmallocUsed": "834112 kB",
            "VmallocChunk": "0 kB",
            "Percpu": "1677312 kB",
            "HardwareCorrupted": "0 kB",
            "AnonHugePages": "0 kB",
            "ShmemHugePages": "0 kB",
            "ShmemPmdMapped": "0 kB",
            "FileHugePages": "0 kB",
            "FilePmdMapped": "0 kB",
            "CmaTotal": "0 kB",
            "CmaFree": "0 kB",
            "HugePages_Total": "0",
            "HugePages_Free": "0",
            "HugePages_Rsvd": "0",
            "HugePages_Surp": "0",
            "Hugepagesize": "524288 kB",
            "Hugetlb": "0 kB"
        },
        "end": "2025-10-07T11:25:02.288648"
    },
    "hostname": "sdumont2nd3007"
}