{
    "1": {
        "start": "2025-11-30T21:27:31.974492",
        "block1": {
            "start": "2025-11-30T21:27:31.974612",
            "end": "2025-11-30T21:27:32.069130",
            "duration": "0.09"
        },
        "save_ckpt1": {
            "start": "2025-11-30T21:27:32.075641",
            "end": "2025-11-30T21:27:32.077017",
            "duration": 0.001376,
            "throughput": 0.006930772648301236
        },
        "end": "2025-11-30T21:27:32.217612",
        "duration": "0.10",
        "eval": {
            "start": "2025-11-30T21:27:32.078269",
            "end": "2025-11-30T21:27:32.215014",
            "duration": "0.14"
        }
    }
}