{
    "1": {
        "start": "2025-10-07T11:14:36.152183",
        "block1": {
            "start": "2025-10-07T11:14:36.152382",
            "end": "2025-10-07T11:15:03.212199",
            "duration": "27.06"
        },
        "end": "2025-10-07T11:15:03.238900",
        "duration": "27.06",
        "eval": {
            "start": "2025-10-07T11:15:03.217501",
            "end": "2025-10-07T11:15:03.235504",
            "duration": "0.02"
        }
    },
    "2": {
        "start": "2025-10-07T11:15:03.238910",
        "block1": {
            "start": "2025-10-07T11:15:03.239236",
            "end": "2025-10-07T11:15:30.050388",
            "duration": "26.81"
        },
        "end": "2025-10-07T11:15:30.058557",
        "duration": "26.81",
        "eval": {
            "start": "2025-10-07T11:15:30.052980",
            "end": "2025-10-07T11:15:30.056949",
            "duration": "0.00"
        }
    },
    "3": {
        "start": "2025-10-07T11:15:30.058566",
        "block1": {
            "start": "2025-10-07T11:15:30.058839",
            "end": "2025-10-07T11:15:56.820433",
            "duration": "26.76"
        },
        "end": "2025-10-07T11:15:56.826056",
        "duration": "26.76",
        "eval": {
            "start": "2025-10-07T11:15:56.822989",
            "end": "2025-10-07T11:15:56.824417",
            "duration": "0.00"
        }
    },
    "4": {
        "start": "2025-10-07T11:15:56.826064",
        "block1": {
            "start": "2025-10-07T11:15:56.826348",
            "end": "2025-10-07T11:16:23.570426",
            "duration": "26.74"
        },
        "end": "2025-10-07T11:16:23.575874",
        "duration": "26.75",
        "eval": {
            "start": "2025-10-07T11:16:23.572974",
            "end": "2025-10-07T11:16:23.574233",
            "duration": "0.00"
        }
    },
    "5": {
        "start": "2025-10-07T11:16:23.575882",
        "block1": {
            "start": "2025-10-07T11:16:23.576165",
            "end": "2025-10-07T11:16:50.320453",
            "duration": "26.74"
        },
        "save_ckpt1": {
            "start": "2025-10-07T11:16:50.322222",
            "end": "2025-10-07T11:16:50.333258",
            "duration": 0.011036,
            "throughput": 0.0008641485288204512
        },
        "end": "2025-10-07T11:16:50.337747",
        "duration": "26.76",
        "eval": {
            "start": "2025-10-07T11:16:50.334852",
            "end": "2025-10-07T11:16:50.336151",
            "duration": "0.00"
        }
    }
}